timg/__init__.py
timg/__main__.py
timg/timglib/__init__.py
timg/timglib/constants.py
timg/timglib/custom_types.py
timg/timglib/errors.py
timg/timglib/utils.py
timg/timglib/timg_api/__init__.py
timg/timglib/timg_api/gitee.py
timg/timglib/timg_api/github.py
timg/timglib/timg_api/imgtu.py
timg/timglib/timg_api/sm.py
typora_upload_image-0.1.7.dist-info/LICENSE
typora_upload_image-0.1.7.dist-info/METADATA
typora_upload_image-0.1.7.dist-info/WHEEL
typora_upload_image-0.1.7.dist-info/entry_points.txt
typora_upload_image-0.1.7.dist-info/top_level.txt
typora_upload_image-0.1.7.dist-info/RECORD
