Metadata-Version: 2.1
Name: typora-upload-image
Version: 0.1.7
Summary: 
Home-page: https://github.com/thep0y/timg
Author: thepoy
Author-email: thepoy@163.com
License: MIT
Keywords: typora image bed upload
Platform: UNKNOWN
Requires-Dist: requests
Requires-Dist: requests-toolbelt
Requires-Dist: pillow
